utiloori/__about__.py
utiloori/__init__.py
utiloori/ansi_color.py
utiloori/calendar.py
utiloori/chatlog.py
utiloori/datatypes.py
utiloori/filepath.py
utiloori/func.py
utiloori/json.py
utiloori/markdown.py
utiloori/pg.py
utiloori/plaintext.py
utiloori-0.4.0.dist-info/METADATA
utiloori-0.4.0.dist-info/WHEEL
utiloori-0.4.0.dist-info/licenses/LICENSE
utiloori-0.4.0.dist-info/RECORD
