Metadata-Version: 2.3
Name: utiloori
Version: 0.4.0
Summary: oori's miscellaneous python toolkit
Project-URL: Documentation, https://github.com/OoriData/utiloori#readme
Project-URL: Issues, https://github.com/OoriData/utiloori/issues
Project-URL: Source, https://github.com/OoriData/utiloori
Author-email: Osi Ogbuji <osita@ogbuji.net>
License: Apache-2.0
Classifier: Development Status :: 4 - Beta
Classifier: Programming Language :: Python
Classifier: Programming Language :: Python :: 3.10
Classifier: Programming Language :: Python :: 3.11
Classifier: Programming Language :: Python :: Implementation :: CPython
Classifier: Programming Language :: Python :: Implementation :: PyPy
Requires-Python: >=3.10
